intercoop/__init__.py
intercoop/apiclient.py
intercoop/apiclient_test.py
intercoop/apiexample.py
intercoop/apiexample_test.py
intercoop/catalog.py
intercoop/catalog_test.py
intercoop/crypto.py
intercoop/crypto_test.py
intercoop/fixtures.py
intercoop/keyring.py
intercoop/keyring_test.py
intercoop/packaging.py
intercoop/packaging_test.py
intercoop/peerinfo.py
intercoop/peerinfo_test.py
intercoop/perfume.py
intercoop/portalexample.py
intercoop/portalexample_test.py
intercoop/remoteuserinfo.py
intercoop/remoteuserinfo_test.py
intercoop/testutils.py
intercoop/translation.py
intercoop/translation_test.py
intercoop/userinfo.py
intercoop/userinfo_test.py
intercoop/somenergia/__init__.py
intercoop/somenergia/userinfo.py
intercoop/somenergia/userinfo_test.py
intercoop-0.2.2.data/scripts/api-example-somacme.py
intercoop-0.2.2.data/scripts/portal-example-somillusio.py
intercoop-0.2.2.data/scripts/validate-intercoop.py
intercoop-0.2.2.dist-info/METADATA
intercoop-0.2.2.dist-info/WHEEL
intercoop-0.2.2.dist-info/top_level.txt
intercoop-0.2.2.dist-info/RECORD
