Metadata-Version: 2.1
Name: intercoop
Version: 0.2.2
Summary: Intercooperation library
Author-email: Som Energia <info@somenergia.coop>
Project-URL: Homepage, https://somenergia.coop
Project-URL: Documentation, https://github.com/som-energia/intercoop
Project-URL: Repository, https://github.com/som-energia/intercoop
Project-URL: Changelog, https://github.com/som-energia/intercoop/blob/master/CHANGELOG.md
Keywords: crossed services,gprd,crossed users
Classifier: Topic :: Office/Business
Classifier: Topic :: Software Development :: Libraries :: Python Modules
Classifier: Intended Audience :: Developers
Classifier: Programming Language :: Python
Classifier: Programming Language :: Python :: 3
Classifier: Framework :: Flask
Classifier: Environment :: Web Environment
Classifier: Natural Language :: Basque
Classifier: Natural Language :: Catalan
Classifier: Natural Language :: Galician
Classifier: Natural Language :: Spanish
Classifier: Development Status :: 4 - Beta
Classifier: License :: OSI Approved :: GNU Affero General Public License v3 or later (AGPLv3+)
Classifier: Operating System :: OS Independent
Requires-Python: >=3.10
Requires-Dist: pycryptodome
Requires-Dist: yamlns>=0.6
Requires-Dist: requests
Requires-Dist: requests-mock
Requires-Dist: flask
Requires-Dist: jsonschema<3
Requires-Dist: erppeek
